CONTRIBUTING.md
LICENSE
MANIFEST.in
README.md
settings.ini
setup.py
fastSE.egg-info/PKG-INFO
fastSE.egg-info/SOURCES.txt
fastSE.egg-info/dependency_links.txt
fastSE.egg-info/entry_points.txt
fastSE.egg-info/not-zip-safe
fastSE.egg-info/requires.txt
fastSE.egg-info/top_level.txt
fastse/__init__.py
fastse/_aot.py
fastse/assemble.py
fastse/cpf.py
fastse/derivatives.py
fastse/helper.py
fastse/io.py
fastse/measurements.py
fastse/nr.py
fastse/performance.py
fastse/pf.py
fastse/precompile.pyd
fastse/precompile310.pyd
fastse/precompile37.pyd
fastse/precompile38.pyd
fastse/precompile39.pyd
fastse/se.py
fastse/tdpf.py
fastse/validation.py