Metadata-Version: 2.1
Name: fastSE
Version: 0.3.0
Summary: A fine-tuned state estimator for power system.
Home-page: https://github.com/mzy2240/fastSE/tree/master/
Author: Zeyu Mao
Author-email: zeyumao2@tamu.edu
License: Apache Software License 2.0
Keywords: state estimation,power system,sparse matrix,JIT,HPC
Platform: UNKNOWN
Classifier: Development Status :: 6 - Mature
Classifier: Intended Audience :: Developers
Classifier: License :: OSI Approved :: Apache Software License
Classifier: Natural Language :: English
Classifier: Programming Language :: Python :: 3.6
Classifier: Programming Language :: Python :: 3.7
Classifier: Programming Language :: Python :: 3.8
Classifier: Programming Language :: Python :: 3.9
Classifier: Programming Language :: Python :: 3.10
Requires-Python: >=3.6
License-File: LICENSE
